pysecrets_docker/__init__.py
pysecrets_docker/main.py
pysecrets_docker-1.0.0.dist-info/LICENSE
pysecrets_docker-1.0.0.dist-info/METADATA
pysecrets_docker-1.0.0.dist-info/WHEEL
pysecrets_docker-1.0.0.dist-info/top_level.txt
pysecrets_docker-1.0.0.dist-info/RECORD
